AUTHORS
LICENSE
MANIFEST.in
README.rst
setup.py
django_formapi.egg-info/PKG-INFO
django_formapi.egg-info/SOURCES.txt
django_formapi.egg-info/dependency_links.txt
django_formapi.egg-info/requires.txt
django_formapi.egg-info/top_level.txt
formapi/__init__.py
formapi/admin.py
formapi/api.py
formapi/calls.py
formapi/models.py
formapi/urls.py
formapi/utils.py
formapi/views.py
formapi/migrations/0001_initial.py
formapi/migrations/0002_auto__add_field_apikey_revoked__add_field_apikey_test.py
formapi/migrations/__init__.py
formapi/static/bootstrap/css/bootstrap-responsive.css
formapi/static/bootstrap/css/bootstrap-responsive.min.css
formapi/static/bootstrap/css/bootstrap.css
formapi/static/bootstrap/css/bootstrap.min.css
formapi/static/bootstrap/img/glyphicons-halflings-white.png
formapi/static/bootstrap/img/glyphicons-halflings.png
formapi/static/bootstrap/js/bootstrap.js
formapi/static/bootstrap/js/bootstrap.min.js
formapi/templates/formapi/404.html
formapi/templates/formapi/500.html
formapi/templates/formapi/base.html
formapi/templates/formapi/api/call.html
formapi/templates/formapi/api/discover.html
formapi/templates/formapi/api/form.html
formapi/templatetags/__init__.py
formapi/templatetags/formapi_utils.py