Metadata-Version: 1.1
Name: django-formapi
Version: 0.2.0
Summary: Django API creation with signed requests utilizing forms for validation.
Home-page: http://github.com/5monkeys/django-formapi
Author: Hannes Ljungberg
Author-email: hannes@5monkeys.se
License: MIT
Download-URL: https://github.com/5monkeys/django-formapi/tarball/0.2.0
Keywords: django,formapi,api,rpc,signed,request,form,validation
Platform: any
Classifier: Programming Language :: Python
Classifier: Programming Language :: Python :: 2
Classifier: Programming Language :: Python :: 2.6
Classifier: Programming Language :: Python :: 2.7
Classifier: Framework :: Django
Classifier: Natural Language :: English
Classifier: Environment :: Web Environment
Classifier: Intended Audience :: Developers
Classifier: License :: OSI Approved :: MIT License
Classifier: Operating System :: OS Independent
Classifier: Topic :: Utilities
Classifier: Topic :: Software Development :: Libraries :: Python Modules
